{
  "kind": "singleType",
  "collectionName": "single_type_forsides",
  "info": {
    "singularName": "single-type-forside",
    "pluralName": "single-type-forsides",
    "displayName": "SingleTypeForside",
    "description": ""
  },
  "options": {
    "draftAndPublish": true
  },
  "pluginOptions": {},
  "attributes": {
    "hero": {
      "type": "component",
      "repeatable": false,
      "component": "tekst.tekst-boks-med-link"
    },
    "video": {
      "type": "component",
      "repeatable": false,
      "component": "tekst.tekst-boks-med-link"
    },
    "traenere_info": {
      "type": "component",
      "repeatable": false,
      "component": "tekst.tekst-boks"
    },
    "medlemskab_info": {
      "type": "component",
      "repeatable": false,
      "component": "tekst.tekst-boks"
    },
    "spoergsmaal": {
      "type": "component",
      "repeatable": false,
      "component": "tekst.tekst-boks"
    },
    "bestyrelsen": {
      "type": "component",
      "repeatable": false,
      "component": "tekst.tekst-boks"
    },
    "kontaktbillede": {
      "type": "string"
    }
  }
}
